hw_wisecloud_analytics_1/__init__.py
hw_wisecloud_analytics_1-7.0.1.dist-info/LICENSE
hw_wisecloud_analytics_1-7.0.1.dist-info/METADATA
hw_wisecloud_analytics_1-7.0.1.dist-info/WHEEL
hw_wisecloud_analytics_1-7.0.1.dist-info/top_level.txt
hw_wisecloud_analytics_1-7.0.1.dist-info/RECORD
