Metadata-Version: 2.1
Name: hw-wisecloud-analytics-1
Version: 7.0.1
Summary: Analytics Kit is a one-stop user behavior analysis platform for products such as mobile apps, web apps, quick apps, quick games, and mini-programs. It offers scenario-specific data collection, management, analysis, and usage, helping enterprises achieve effective user acquisition, product optimization, precise operations, and business growth.
Home-page: https://developer.huawei.com/consumer/en/doc/development/HMSCore-Guides/introduction-0000001050745149
Author: Huawei HMS Core
Author-email: hms@huawei.com
Project-URL: Documentation, https://developer.huawei.com/consumer/en/doc/development/HMSCore-Guides/introduction-0000001050745149
Project-URL: Bug Reports, https://developer.huawei.com/consumer/en/doc/development/HMSCore-Guides/introduction-0000001050745149/issues
Project-URL: Source Code, https://developer.huawei.com/consumer/en/doc/development/HMSCore-Guides/introduction-0000001050745149
Keywords: example,pypi,package
Classifier: Development Status :: 5 - Production/Stable
Classifier: Intended Audience :: Developers
Classifier: Topic :: Software Development :: Build Tools
Classifier: Programming Language :: Python :: 3
Classifier: Programming Language :: Python :: 3.6
Classifier: Programming Language :: Python :: 3.7
Classifier: Programming Language :: Python :: 3.8
Classifier: Programming Language :: Python :: 3.9
Classifier: Programming Language :: Python :: 3 :: Only
Classifier: License :: OSI Approved :: MIT License
Classifier: Operating System :: OS Independent
Requires-Python: >=3.6
License-File: LICENSE
